pdf_mangler/__init__.py
pdf_mangler/__main__.py
pdf_mangler/defaults.yaml
pdf_mangler/mangler.py
pdf_mangler/text_utils.py
pdf_mangler/fonts/adobe-latin-1.txt
pdf_mangler/fonts/adobe-latin-2.txt
pdf_mangler/fonts/adobe-latin-3.txt
pdf_mangler/fonts/adobe-latin-4-precomposed.txt
pdf_mangler/fonts/adobe-latin-5-precomposed.txt
pdf_mangler/fonts/glyphlist.txt
pdf_mangler-0.1.6.dist-info/LICENSE
pdf_mangler-0.1.6.dist-info/METADATA
pdf_mangler-0.1.6.dist-info/WHEEL
pdf_mangler-0.1.6.dist-info/entry_points.txt
pdf_mangler-0.1.6.dist-info/top_level.txt
pdf_mangler-0.1.6.dist-info/RECORD
