Metadata-Version: 2.1
Name: pdf-mangler
Version: 0.1.6
Summary: Anonymize and obfuscate PDF info while retaining structure
Author: Charlotte Curtis
Author-email: ccurtis@mtroyal.ca
License: Mozilla Public License Version 2.0
Project-URL: repository, https://github.com/cfcurtis/pdf-mangler
Keywords: pdf,utility,anonymization,privacy
Classifier: Programming Language :: Python :: 3
Classifier: License :: OSI Approved :: Mozilla Public License 2.0 (MPL 2.0)
Classifier: Operating System :: OS Independent
Requires-Python: >=3.8
License-File: LICENSE
Requires-Dist: pikepdf >=9.1.1
Requires-Dist: tqdm
Requires-Dist: PyYAML
Provides-Extra: dev
Requires-Dist: pytest ; extra == 'dev'
Requires-Dist: pre-commit ; extra == 'dev'
Requires-Dist: black ; extra == 'dev'
